Workbook

Sheet Dashboard
A1: Retail Sales & Performance Dashboard
A4: TOTAL SALES | C4: Total PROFIT | E4: PROFIT MARGIN | G4: TOTAL ORDERS | I4: AVG ORDER
A5: =analysis!B1 -> 48375149 | C5: =analysis!B2 -> 6923158.3 | E5: =analysis!B3 -> 0.14311394 | G5: =analysis!B4 -> 1500 | I5: =analysis!B5 -> 32250.099
A46: KEY BUSINESS INSIGHTS
A47: • South region generated the highest sales at ₹1.40 Cr.
A48: • Electronics was the largest sales category at ₹3.86 Cr.
A49: • Business Laptop was the top-selling product at ₹1.42 Cr.
A50: • April recorded the lowest monthly sales at ₹27.91 L.
A51: • Office Supplies had the highest category profit margin at 23.47%.
A52: • December recorded the highest monthly sales at ₹50.75 L.

Sheet analysis
A1: Totalsales | B1: =SUM(retailsales[Sales]) -> 48375149
A2: Totalprofit | B2: =SUM(retailsales[Profit]) -> 6923158.3
A3: Profitmargin | B3: =B2/B1 -> 0.14311394
A4: Totalorders | B4: =COUNTA(retailsales[Order_ID]) -> 1500
A5: Aversgeordervalue | B5: =B1/B4 -> 32250.099
A8: category | B8: sales | C8: profit | D8: profitmargin
A9: Electronics | B9: 38550940 | C9: 5109995.4 | D9: =C9/B9 -> 0.13255177
A10: Furniture | B10: 9364611.3 | C10: 1705281.2 | D10: =C10/B10 -> 0.18209845
A11: Officesupplies | B11: 459598.1 | C11: 107881.74 | D11: =C11/B11 -> 0.2347306
A14: Region | B14: Sales | C14: Profit | D14: Profitmargin
A15: East | B15: 10996134 | C15: 1655647 | D15: =C15/B15 -> 0.15056628
A16: North | B16: 12222772 | C16: 1704299.6 | D16: =C16/B16 -> 0.13943642
A17: South | B17: 13961115 | C17: 1943587.9 | D17: =C17/B17 -> 0.13921437
A18: West | B18: 11195128 | C18: 1619623.8 | D18: =C18/B18 -> 0.14467221
A21: Product | B21: Sales | C21: Profit | D21: Profitmargin
A22: Businesslaptop | B22: 14208075 | C22: 1964313.8 | D22: =C22/B22 -> 0.13825333
A23: Studentlaptop | B23: 10698034 | C23: 1343276.4 | D23: =C23/B23 -> 0.12556293
A24: Smartphonepro | B24: 9132833.3 | C24: 1201088.2 | D24: =C24/B24 -> 0.13151321
A25: Smartphonelite | B25: 3827442.3 | C25: 512066 | D25: 0.13378804
A26: Storagecabinet | B26: 3494627.2 | C26: 638095.33 | D26: 0.18259325
A29: Month | B29: Sales | C29: Profit | D29: Profit margin
A30: Jan | B30: 4558784 | C30: 68304.51 | D30: =C30/B30 -> 0.014983055
A31: Feb | B31: 4461477.4 | C31: 583321.72 | D31: =C31/B31 -> 0.13074631
A32: Mar | B32: 3697121.9 | C32: 517785.07 | D32: =C32/B32 -> 0.14005085
A33: Apr | B33: 2790935.4 | C33: 336738.63 | D33: =C33/B33 -> 0.1206544
A34: May | B34: 3858104.9 | C34: 580731.37 | D34: =C34/B34 -> 0.15052244
A35: June | B35: 3985541.6 | C35: 615347.37 | D35: =C35/B35 -> 0.15439492
A36: July | B36: 4392458.1 | C36: 598438.52 | D36: =C36/B36 -> 0.13624228
A37: Aug | B37: 4809282.8 | C37: 715441.29 | D37: =C37/B37 -> 0.14876258
A38: Sep | B38: 4122590.7 | C38: 620265.18 | D38: =C38/B38 -> 0.15045519
A39: Oct | B39: 3425718.3 | C39: 510030.88 | D39: =C39/B39 -> 0.1488829
A40: Nov | B40: 3198513.8 | C40: 439376.29 | D40: =C40/B40 -> 0.13736889
A41: Dec | B41: 5074620.5 | C41: 725337.51 | D41: =C41/B41 -> 0.14293434

Sheet Raw_Data
A1: Order_ID | B1: Order_Date | C1: Customer_ID | D1: Customer_Name | E1: Segment | F1: Region | G1: State | H1: City | I1: Category | J1: Sub_Category | K1: Product_Name | L1: Quantity | M1: Unit_Price | N1: Discount | O1: Sales | P1: Profit | Q1: Payment_Mode
A2: ORD-01344 | B2: 45658 | C2: CUST-0235 | D2: Customer 0235 | E2: Corporate | F2: West | G2: Gujarat | H2: Ahmedabad | I2: Furniture | J2: Tables | K2: Office Desk | L2: 1 | M2: 12337.2 | N2: 0.15 | O2: 10486.62 | P2: 1136.21 | Q2: UPI
A3: ORD-00044 | B3: 45658 | C3: CUST-0173 | D3: Customer 0173 | E3: Consumer | F3: South | G3: Tamil Nadu | H3: Chennai | I3: Electronics | J3: Phones | K3: Smartphone Pro | L3: 2 | M3: 40399.04 | N3: 0 | O3: 80798.08 | P3: 7793.27 | Q3: Cash
A4: ORD-00421 | B4: 45658 | C4: CUST-0195 | D4: Customer 0195 | E4: Small Business | F4: North | G4: Uttar Pradesh | H4: Lucknow | I4: Office Supplies | J4: Storage | K4: File Organizer | L4: 2 | M4: 716.15 | N4: 0.2 | O4: 1145.84 | P4: 108.76 | Q4: Card
A5: ORD-01084 | B5: 45658 | C5: CUST-0190 | D5: Customer 0190 | E5: Consumer | F5: South | G5: Karnataka | H5: Bengaluru | I5: Electronics | J5: Accessories | K5: Wireless Mouse | L5: 2 | M5: 1257.97 | N5: 0.2 | O5: 2012.75 | P5: 283.99 | Q5: UPI
A6: ORD-00134 | B6: 45658 | C6: CUST-0080 | D6: Customer 0080 | E6: Consumer | F6: East | G6: Odisha | H6: Bhubaneswar | I6: Furniture | J6: Storage | K6: Storage Cabinet | L6: 1 | M6: 14399.79 | N6: 0.15 | O6: 12239.82 | P6: 1488.99 | Q6: UPI
A7: ORD-00985 | B7: 45659 | C7: CUST-0114 | D7: Customer 0114 | E7: Consumer | F7: South | G7: Karnataka | H7: Bengaluru | I7: Office Supplies | J7: Storage | K7: File Organizer | L7: 1 | M7: 778.13 | N7: 0 | O7: 778.13 | P7: 251.8 | Q7: UPI
A8: ORD-00843 | B8: 45659 | C8: CUST-0061 | D8: Customer 0061 | E8: Consumer | F8: South | G8: Telangana | H8: Hyderabad | I8: Electronics | J8: Laptops | K8: Student Laptop | L8: 2 | M8: 46098.43 | N8: 0 | O8: 92196.86 | P8: 8970.77 | Q8: Net Banking
A9: ORD-00014 | B9: 45659 | C9: CUST-0052 | D9: Customer 0052 | E9: Consumer | F9: South | G9: Karnataka | H9: Bengaluru | I9: Office Supplies | J9: Paper | K9: Printer Paper | L9: 3 | M9: 434.16 | N9: 0.1 | O9: 1172.23 | P9: 390.21 | Q9: Card
A10: ORD-01215 | B10: 45660 | C10: CUST-0082 | D10: Customer 0082 | E10: Consumer | F10: South | G10: Tamil Nadu | H10: Chennai | I10: Electronics | J10: Laptops | K10: Student Laptop | L10: 3 | M10: 48250.63 | N10: 0.05 | O10: 137514.3 | P10: 20572.88 | Q10: Card
A11: ORD-00447 | B11: 45660 | C11: CUST-0178 | D11: Customer 0178 | E11: Consumer | F11: North | G11: Uttar Pradesh | H11: Lucknow | I11: Office Supplies | J11: Paper | K11: Printer Paper | L11: 2 | M11: 448.97 | N11: 0.05 | O11: 853.04 | P11: 248.53 | Q11: Net Banking
A12: ORD-01430 | B12: 45660 | C12: CUST-0255 | D12: Customer 0255 | E12: Consumer | F12: South | G12: Telangana | H12: Hyderabad | I12: Furniture | J12: Chairs | K12: Ergonomic Chair | L12: 3 | M12: 8866.1 | N12: 0.1 | O12: 23938.47 | P12: 5118.76 | Q12: Net Banking
A13: ORD-01163 | B13: 45660 | C13: CUST-0026 | D13: Customer 0026 | E13: Consumer | F13: North | G13: Rajasthan | H13: Jaipur | I13: Electronics | J13: Accessories | K13: Keyboard | L13: 1 | M13: 1744.13 | N13: 0 | O13: 1744.13 | P13: 147.29 | Q13: Card
... A1501: ORD-01423 | B1501: 46022 | C1501: CUST-0126 | D1501: Customer 0126 | E1501: Consumer | F1501: South | G1501: Karnataka | H1501: Bengaluru | I1501: Furniture | J1501: Tables | K1501: Study Table | L1501: 2 | M1501: 6404.55 | N1501: 0.15 | O1501: 10887.74 | P1501: 1541.58 | Q1501: Card

Sheet categoryanalysis
A3: Row Labels | B3: Sum of Sales | C3: Sum of Profit
A4: Electronics | B4: 38550940 | C4: 5109995.4
A5: Furniture | B5: 9364611.3 | C5: 1705281.2
A6: Office Supplies | B6: 459598.1 | C6: 107881.74
A7: Grand Total | B7: 48375149 | C7: 6923158.3
C9: =GETPIVOTDATA("Sum of Sales",$A$3,"Category","Electronics") -> 38550940

Sheet Regionalanalysis
A3: Row Labels | B3: Sum of Sales | C3: Sum of Profit
A4: East | B4: 10996134 | C4: 1655647
A5: North | B5: 12222772 | C5: 1704299.6
A6: South | B6: 13961115 | C6: 1943587.9
A7: West | B7: 11195128 | C7: 1619623.8
A8: Grand Total | B8: 48375149 | C8: 6923158.3

Sheet Productanalysis
A3: Row Labels | B3: Sum of Sales | C3: Sum of Profit
A4: Business Laptop | B4: 14208075 | C4: 1964313.8
A5: Student Laptop | B5: 10698034 | C5: 1343276.4
A6: Smartphone Pro | B6: 9132833.3 | C6: 1201088.2
A7: Smartphone Lite | B7: 3827442.3 | C7: 512066
A8: Storage Cabinet | B8: 3494627.2 | C8: 638095.33
A9: Office Desk | B9: 2603446.1 | C9: 454148.96
A10: Study Table | B10: 1723076.4 | C10: 314547.14
A11: Ergonomic Chair | B11: 1543461.5 | C11: 298489.74
A12: Keyboard | B12: 402280.56 | C12: 52538.18
A13: Wireless Mouse | B13: 282274.46 | C13: 36712.85
A14: File Organizer | B14: 174057.78 | C14: 40018.32
A15: Notebook Pack | B15: 114153.66 | C15: 26643.65
... A18: Grand Total | B18: 48375149 | C18: 6923158.3

Sheet Monthy analysis
A3: Row Labels | B3: Sum of Sales | C3: Sum of Profit
A4: Jan | B4: 4558784 | C4: 680304.51
A5: Feb | B5: 4461477.4 | C5: 583321.72
A6: Mar | B6: 3697121.9 | C6: 517785.07
A7: Apr | B7: 2790935.4 | C7: 336738.63
A8: May | B8: 3858104.9 | C8: 580771.37
A9: Jun | B9: 3985541.6 | C9: 615347.37
A10: Jul | B10: 4392458.1 | C10: 598438.52
A11: Aug | B11: 4809282.8 | C11: 715441.29
A12: Sep | B12: 4122590.7 | C12: 620265.18
A13: Oct | B13: 3425718.3 | C13: 510030.88
A14: Nov | B14: 3198513.8 | C14: 439376.29
A15: Dec | B15: 5074620.5 | C15: 725337.51
A16: Grand Total | B16: 48375149 | C16: 6923158.3
